[
  {
    "type": "BUY",
    "check": 5,
    "timestamp": "2026-05-24T20:50:35.395880+00:00",
    "price": 1797.09,
    "eur_spent": 1800.0,
    "coin_bought": 1.00161928,
    "balance_after": 200.0,
    "coin_after": 1.00161928
  },
  {
    "type": "BUY",
    "check": 6,
    "timestamp": "2026-05-24T20:55:28.846819+00:00",
    "price": 1796.77,
    "eur_spent": 180.0,
    "coin_bought": 0.10017977,
    "balance_after": 20.0,
    "coin_after": 1.10179905
  },
  {
    "type": "BUY",
    "check": 7,
    "timestamp": "2026-05-24T21:00:56.980481+00:00",
    "price": 1796.67,
    "eur_spent": 18.0,
    "coin_bought": 0.01001853,
    "balance_after": 2.0,
    "coin_after": 1.11181759
  }
]